verifyf/__init__.py
verifyf/verify.py
verifyf-1.0.0.dist-info/METADATA
verifyf-1.0.0.dist-info/WHEEL
verifyf-1.0.0.dist-info/top_level.txt
verifyf-1.0.0.dist-info/RECORD
