Metadata-Version: 2.1
Name: verifyf
Version: 1.0.0
Summary: Python package to verify Embeddings
Home-page: UNKNOWN
Author: 
License: UNKNOWN
Platform: UNKNOWN
Requires-Dist: numpy
Requires-Dist: scikit-learn
